yabasi/Version.py
yabasi/__init__.py
yabasi/bas.py
yabasi/parsetab.py
yabasi/tokenizer.py
yabasi-2.1.dist-info/LICENSE
yabasi-2.1.dist-info/METADATA
yabasi-2.1.dist-info/WHEEL
yabasi-2.1.dist-info/entry_points.txt
yabasi-2.1.dist-info/top_level.txt
yabasi-2.1.dist-info/RECORD
