Metadata-Version: 2.1
Name: yabasi
Version: 2.1
Summary: Minimal BASIC interpreter for running MININEC
Home-page: https://github.com/schlatterbeck/yabasi
Author: Ralf Schlatterbeck
Author-email: Ralf Schlatterbeck <rsc@runtux.com>
License: MIT License
Project-URL: Homepage, https://github.com/schlatterbeck/yabasi
Project-URL: Bug Tracker, https://github.com/schlatterbeck/yabasi/issues
Platform: Any
Classifier: Development Status :: 4 - Beta
Classifier: License :: OSI Approved :: MIT License
Classifier: Operating System :: OS Independent
Classifier: Intended Audience :: Science/Research
Classifier: Intended Audience :: Other Audience
Classifier: Topic :: Communications :: Ham Radio
Classifier: Programming Language :: Python
Classifier: Programming Language :: Python :: 3.11
Classifier: Programming Language :: Python :: 3.12
Requires-Python: >=3.11
License-File: LICENSE
Requires-Dist: numpy
Requires-Dist: ply
Requires-Dist: pillow
